cmdrnafold/RNA.py
cmdrnafold/__init__.py
cmdrnafold-0.0.1.dist-info/LICENSE
cmdrnafold-0.0.1.dist-info/METADATA
cmdrnafold-0.0.1.dist-info/WHEEL
cmdrnafold-0.0.1.dist-info/RECORD
