Metadata-Version: 2.1
Name: cmdrnafold
Version: 0.0.1
Summary: Primitive Vienna RNA fold interface via the commandline.
Home-page: https://github.com/retospect/cmdrnafold
License: GPL-3
Keywords: biopython,rna
Author: Reto Stamm
Maintainer: Reto Stamm
Classifier: License :: Other/Proprietary License
Classifier: Programming Language :: Python :: 2
Classifier: Programming Language :: Python :: 2.7
Classifier: Programming Language :: Python :: 3
Classifier: Programming Language :: Python :: 3.4
Classifier: Programming Language :: Python :: 3.5
Classifier: Programming Language :: Python :: 3.6
Classifier: Programming Language :: Python :: 3.7
Classifier: Programming Language :: Python :: 3.8
Classifier: Programming Language :: Python :: 3.9
Classifier: Programming Language :: Python :: 3.10
Classifier: Programming Language :: Python :: 3.11
Project-URL: Repository, https://github.com/retospect/cmdrnafold
